[
    {
        "id": 12693126,
        "title_fa": "نیم تنه زنانه کلوتو مدل KATJA - GLDCRM",
        "price": {},
        "image": {
            "pic1": "https://dkstatics-public.digikala.com/digikala-products/956b6b8a5e77953f8a580a69c61dd7d71ff21716_1695027367.jpg?x-oss-process=image/resize,m_lfit,h_800,w_800/quality,q_90"
        },
        "attributes": [
            {
                "key": "جنس",
                "value": [
                    "نخ"
                ]
            },
            {
                "key": "طرح",
                "value": [
                    "طرح‌دار"
                ]
            },
            {
                "key": "قد",
                "value": [
                    "نیم تنه"
                ]
            },
            {
                "key": "مدل یقه",
                "value": [
                    "دکلته"
                ]
            },
            {
                "key": "نوع آستین",
                "value": [
                    "بدون آستین"
                ]
            },
            {
                "key": "تنخور لباس",
                "value": [
                    "معمولی"
                ]
            },
            {
                "key": "نحوه بسته شدن",
                "value": [
                    "بندی"
                ]
            },
            {
                "key": "مورد استفاده",
                "value": [
                    "روزمره",
                    "مهمانی"
                ]
            },
            {
                "key": "جزئیات",
                "value": [
                    "مناسب برای  سایز های ۴۰ الی  ۴۲"
                ]
            },
            {
                "key": "نگهداری",
                "value": [
                    "- پیشنهاد می شود شستشوی این لباس توسط خشکشویی های معتبر انجام شود"
                ]
            },
            {
                "key": "کد کالای محصول",
                "value": [
                    "۲۲۲۲۱۰۹۰۹۰۹۷"
                ]
            },
            {
                "key": "کشور مبدا برند",
                "value": [
                    "ایران"
                ]
            },
            {
                "key": "کشور تولید کننده",
                "value": [
                    "ایران"
                ]
            }
        ]
    }
]