[
    {
        "id": 12980922,
        "title_fa": "کراپ‌تاپ زنانه مدل پد متحرک وارداتی طرح گل پشت چین دار کد 55555",
        "price": {},
        "image": {
            "pic1": "https://dkstatics-public.digikala.com/digikala-products/33695e2eb7b99616d36cc6d109ec9e1ac8a3f93e_1697265402.jpg?x-oss-process=image/resize,m_lfit,h_800,w_800/quality,q_90"
        },
        "attributes": [
            {
                "key": "جنس",
                "value": [
                    "اسفنجی",
                    "گیپور"
                ]
            },
            {
                "key": "طرح",
                "value": [
                    "طرح‌دار"
                ]
            },
            {
                "key": "قد",
                "value": [
                    "نیم تنه"
                ]
            },
            {
                "key": "مدل یقه",
                "value": [
                    "باز"
                ]
            },
            {
                "key": "نوع آستین",
                "value": [
                    "بدون آستین"
                ]
            },
            {
                "key": "تنخور لباس",
                "value": [
                    "جذب"
                ]
            },
            {
                "key": "مورد استفاده",
                "value": [
                    "اسپرت",
                    "روزمره",
                    "مهمانی"
                ]
            },
            {
                "key": "کشور تولید کننده",
                "value": [
                    "چین"
                ]
            }
        ]
    }
]