[
    {
        "id": 15121487,
        "title_fa": "کراپ‌تاپ زنانه اسمارا مدل03 بسته 2 عددی",
        "price": {},
        "image": {
            "pic1": "https://dkstatics-public.digikala.com/digikala-products/526bc32017ecdce7372619a7d0f28b7de0791e81_1713428298.jpg?x-oss-process=image/resize,m_lfit,h_800,w_800/quality,q_90"
        },
        "attributes": [
            {
                "key": "جنس",
                "value": [
                    "الاستین",
                    "کتان"
                ]
            },
            {
                "key": "طرح",
                "value": [
                    "طرح‌دار"
                ]
            },
            {
                "key": "قد",
                "value": [
                    "روی کمر"
                ]
            },
            {
                "key": "مدل یقه",
                "value": [
                    "گرد"
                ]
            },
            {
                "key": "نوع آستین",
                "value": [
                    "حلقه‌ای"
                ]
            },
            {
                "key": "تنخور لباس",
                "value": [
                    "جذب"
                ]
            },
            {
                "key": "نحوه بسته شدن",
                "value": [
                    "جلو بسته"
                ]
            },
            {
                "key": "ویژگی‌های تخصصی",
                "value": [
                    "انعطاف پذیر"
                ]
            },
            {
                "key": "مورد استفاده",
                "value": [
                    "اسپرت",
                    "روزمره",
                    "اداری و رسمی",
                    "مهمانی"
                ]
            },
            {
                "key": "کشور مبدا برند",
                "value": [
                    "آلمان"
                ]
            },
            {
                "key": "کشور تولید کننده",
                "value": [
                    "آلمان"
                ]
            }
        ]
    }
]