[
    {
        "id": 15761694,
        "title_fa": "تاپ زنانه مدل گیپور کد 3385",
        "price": {},
        "image": {
            "pic1": "https://dkstatics-public.digikala.com/digikala-products/fb92000e788b22300b2ed44a1a4b4e49ff220ae0_1718103171.jpg?x-oss-process=image/resize,m_lfit,h_800,w_800/quality,q_90"
        },
        "attributes": [
            {
                "key": "نوع تاپ و نیم تنه زنانه",
                "value": [
                    "تاپ"
                ]
            },
            {
                "key": "جنس",
                "value": [
                    "پنبه"
                ]
            },
            {
                "key": "طرح",
                "value": [
                    "راه‌راه"
                ]
            },
            {
                "key": "قد",
                "value": [
                    "روی کمر"
                ]
            },
            {
                "key": "مدل یقه",
                "value": [
                    "هفت"
                ]
            },
            {
                "key": "نوع آستین",
                "value": [
                    "بدون آستین"
                ]
            },
            {
                "key": "تنخور لباس",
                "value": [
                    "جذب"
                ]
            },
            {
                "key": "مدل بند لباس",
                "value": [
                    "معمولی"
                ]
            },
            {
                "key": "مورد استفاده",
                "value": [
                    "اسپرت",
                    "روزمره",
                    "مهمانی"
                ]
            }
        ]
    }
]