[
    {
        "id": 8754257,
        "title_fa": "تاپ زنانه مالدینی مدل Top-101",
        "price": {},
        "image": {
            "pic1": "https://dkstatics-public.digikala.com/digikala-products/7401283d47ca8d6081bea6d5230332b8b6f0139e_1655282552.jpg?x-oss-process=image/resize,m_lfit,h_800,w_800/quality,q_90"
        },
        "attributes": [
            {
                "key": "جنس",
                "value": [
                    "پنبه",
                    "پنبه تیپ لاکرا",
                    "پنبه یکرو"
                ]
            },
            {
                "key": "طرح",
                "value": [
                    "چاپ"
                ]
            },
            {
                "key": "قد",
                "value": [
                    "روی باسن"
                ]
            },
            {
                "key": "مدل یقه",
                "value": [
                    "باز"
                ]
            },
            {
                "key": "نوع آستین",
                "value": [
                    "بدون آستین"
                ]
            },
            {
                "key": "تنخور لباس",
                "value": [
                    "جذب"
                ]
            },
            {
                "key": "مدل بند لباس",
                "value": [
                    "باریک"
                ]
            },
            {
                "key": "نحوه بسته شدن",
                "value": [
                    "جلو بسته"
                ]
            },
            {
                "key": "ویژگی‌های تخصصی",
                "value": [
                    "قابلیت گردش هوا",
                    "انعطاف پذیر"
                ]
            },
            {
                "key": "مورد استفاده",
                "value": [
                    "اسپرت",
                    "روزمره",
                    "مهمانی"
                ]
            },
            {
                "key": "نگهداری",
                "value": [
                    "xفقط با مایع لباس شویی شستشو شود x\r\n در زمان شستشو حتما با آب سرد یا ولرم شسته شود x\r\nمی توانید از نرم کننده می توانید استفاده کنید x\r\nxزمان شستشوی تاپ یا شلوار و یا شلوارک را پشت رو کنیدx\r\nxاز خشک کن می توانید استفاده کنید x\r\nاز پودر و یا تاید استفاده نکنید !!"
                ]
            }
        ]
    }
]