[
    {
        "id": 15073510,
        "title_fa": "کراپ‌تی شرت آستین کوتاه زنانه مدل دوچرخه کد 3",
        "price": {},
        "image": {
            "pic1": "https://dkstatics-public.digikala.com/digikala-products/cfd4ceb2419a10b6531136448db7a7310ad46b18_1712686104.jpg?x-oss-process=image/resize,m_lfit,h_800,w_800/quality,q_90"
        },
        "attributes": [
            {
                "key": "جنس",
                "value": [
                    "پنبه یکرو"
                ]
            },
            {
                "key": "طرح",
                "value": [
                    "چاپ"
                ]
            },
            {
                "key": "قد",
                "value": [
                    "روی کمر"
                ]
            },
            {
                "key": "تنخور لباس",
                "value": [
                    "معمولی"
                ]
            },
            {
                "key": "مدل یقه",
                "value": [
                    "گرد"
                ]
            },
            {
                "key": "نوع آستین",
                "value": [
                    "کوتاه"
                ]
            },
            {
                "key": "مورد استفاده",
                "value": [
                    "اسپرت"
                ]
            }
        ]
    }
]