[
    {
        "id": 10338642,
        "title_fa": "",
        "price": {},
        "image": {
            "pic1": "https://dkstatics-public.digikala.com/digikala-products/a446bb954edbb9475ce9542472575bc034324f36_1672732200.jpg?x-oss-process=image/resize,m_lfit,h_800,w_800/quality,q_90"
        },
        "attributes": [
            {
                "key": "جنس",
                "value": [
                    "پنبه"
                ]
            },
            {
                "key": "طرح",
                "value": [
                    "چاپ"
                ]
            },
            {
                "key": "قد",
                "value": [
                    "روی باسن"
                ]
            },
            {
                "key": "تنخور لباس",
                "value": [
                    "معمولی"
                ]
            },
            {
                "key": "مدل یقه",
                "value": [
                    "گرد"
                ]
            },
            {
                "key": "نوع آستین",
                "value": [
                    "کوتاه"
                ]
            },
            {
                "key": "مورد استفاده",
                "value": [
                    "اسپرت",
                    "روزمره",
                    "مهمانی"
                ]
            },
            {
                "key": "کد کالای محصول",
                "value": [
                    "۳۷۵"
                ]
            }
        ]
    }
]