[
    {
        "id": 12554448,
        "title_fa": "تی شرت آستین کوتاه زنانه 27 مدل Spider Man Logo کد MH1547",
        "price": {},
        "image": {
            "pic1": "https://dkstatics-public.digikala.com/digikala-products/ce76b7b17b0224846f5128b49769af489b2f6982_1693637182.jpg?x-oss-process=image/resize,m_lfit,h_800,w_800/quality,q_90"
        },
        "attributes": [
            {
                "key": "جنس",
                "value": [
                    "پنبه",
                    "نخ"
                ]
            },
            {
                "key": "طرح",
                "value": [
                    "چاپ"
                ]
            },
            {
                "key": "قد",
                "value": [
                    "روی باسن"
                ]
            },
            {
                "key": "تنخور لباس",
                "value": [
                    "معمولی"
                ]
            },
            {
                "key": "مدل یقه",
                "value": [
                    "گرد"
                ]
            },
            {
                "key": "نوع آستین",
                "value": [
                    "کوتاه"
                ]
            },
            {
                "key": "مورد استفاده",
                "value": [
                    "اسپرت",
                    "روزمره"
                ]
            }
        ]
    }
]