[
    {
        "id": 13002880,
        "title_fa": "کراپ‌تاپ آستین کوتاه زنانه مدل c310 طرح هالوین",
        "price": {},
        "image": {
            "pic1": "https://dkstatics-public.digikala.com/digikala-products/246ca3b4e5d700b115a1e153e932307a1b8ec767_1697448434.jpg?x-oss-process=image/resize,m_lfit,h_800,w_800/quality,q_90"
        },
        "attributes": [
            {
                "key": "جنس",
                "value": [
                    "الیاف نخی",
                    "پلی استر"
                ]
            },
            {
                "key": "طرح",
                "value": [
                    "چاپ"
                ]
            },
            {
                "key": "قد",
                "value": [
                    "نیم تنه"
                ]
            },
            {
                "key": "تنخور لباس",
                "value": [
                    "معمولی"
                ]
            },
            {
                "key": "مدل یقه",
                "value": [
                    "گرد"
                ]
            },
            {
                "key": "نوع آستین",
                "value": [
                    "کوتاه"
                ]
            },
            {
                "key": "مورد استفاده",
                "value": [
                    "اسپرت",
                    "روزمره",
                    "مهمانی"
                ]
            }
        ]
    }
]