[
    {
        "id": 13093849,
        "title_fa": "تی شرت آستین کوتاه زنانه آدور مدل شاهنامه رنگ سفید",
        "price": {},
        "image": {
            "pic1": "https://dkstatics-public.digikala.com/digikala-products/f41a0f6762f896d298355eedede491df2e4d6508_1698151515.jpg?x-oss-process=image/resize,m_lfit,h_800,w_800/quality,q_90"
        },
        "attributes": [
            {
                "key": "جنس",
                "value": [
                    "الیاف نخی"
                ]
            },
            {
                "key": "طرح",
                "value": [
                    "چاپ"
                ]
            },
            {
                "key": "قد",
                "value": [
                    "روی باسن"
                ]
            },
            {
                "key": "تنخور لباس",
                "value": [
                    "معمولی"
                ]
            },
            {
                "key": "مدل یقه",
                "value": [
                    "گرد"
                ]
            },
            {
                "key": "نوع آستین",
                "value": [
                    "کوتاه"
                ]
            },
            {
                "key": "مورد استفاده",
                "value": [
                    "روزمره"
                ]
            }
        ]
    }
]