[
    {
        "id": 14196733,
        "title_fa": "تی شرت آستین کوتاه زنانه مدل t 126 طرح پاندا",
        "price": {},
        "image": {
            "pic1": "https://dkstatics-public.digikala.com/digikala-products/aaf9ead8d5b51aa31578b39da2aa420c2234956a_1705945492.jpg?x-oss-process=image/resize,m_lfit,h_800,w_800/quality,q_90"
        },
        "attributes": [
            {
                "key": "جنس",
                "value": [
                    "الیاف نخی",
                    "پلی استر"
                ]
            },
            {
                "key": "طرح",
                "value": [
                    "چاپ"
                ]
            },
            {
                "key": "قد",
                "value": [
                    "روی باسن"
                ]
            },
            {
                "key": "تنخور لباس",
                "value": [
                    "معمولی"
                ]
            },
            {
                "key": "مدل یقه",
                "value": [
                    "گرد"
                ]
            },
            {
                "key": "نوع آستین",
                "value": [
                    "کوتاه"
                ]
            },
            {
                "key": "مورد استفاده",
                "value": [
                    "اسپرت",
                    "روزمره",
                    "مهمانی"
                ]
            }
        ]
    }
]