[
    {
        "id": 14410139,
        "title_fa": "کراپ‌تی شرت آستین کوتاه زنانه مدل 00143 CHW",
        "price": {},
        "image": {
            "pic1": "https://dkstatics-public.digikala.com/digikala-products/4e2468032989309e4b589cd8139f87887176332c_1707808826.jpg?x-oss-process=image/resize,m_lfit,h_800,w_800/quality,q_90"
        },
        "attributes": [
            {
                "key": "جنس",
                "value": [
                    "اسپان"
                ]
            },
            {
                "key": "طرح",
                "value": [
                    "چاپ"
                ]
            },
            {
                "key": "قد",
                "value": [
                    "روی کمر"
                ]
            },
            {
                "key": "تنخور لباس",
                "value": [
                    "معمولی"
                ]
            },
            {
                "key": "مدل یقه",
                "value": [
                    "گرد"
                ]
            },
            {
                "key": "نوع آستین",
                "value": [
                    "کوتاه"
                ]
            },
            {
                "key": "مورد استفاده",
                "value": [
                    "اسپرت",
                    "روزمره",
                    "مهمانی"
                ]
            }
        ]
    }
]