[
    {
        "id": 15079536,
        "title_fa": "کراپ‌تی شرت آستین کوتاه زنانه مدل خرگوش‌ کد 15",
        "price": {},
        "image": {
            "pic1": "https://dkstatics-public.digikala.com/digikala-products/faef08fb868031ff84a794d6ccebd87c859ca57b_1712775171.jpg?x-oss-process=image/resize,m_lfit,h_800,w_800/quality,q_90"
        },
        "attributes": [
            {
                "key": "جنس",
                "value": [
                    "پنبه یکرو"
                ]
            },
            {
                "key": "طرح",
                "value": [
                    "چاپ"
                ]
            },
            {
                "key": "قد",
                "value": [
                    "روی کمر"
                ]
            },
            {
                "key": "تنخور لباس",
                "value": [
                    "معمولی"
                ]
            },
            {
                "key": "مدل یقه",
                "value": [
                    "گرد"
                ]
            },
            {
                "key": "نوع آستین",
                "value": [
                    "کوتاه"
                ]
            },
            {
                "key": "مورد استفاده",
                "value": [
                    "اسپرت"
                ]
            }
        ]
    }
]