[
    {
        "id": 15074489,
        "title_fa": "کراپ‌تی شرت آستین کوتاه زنانه مدل 1",
        "price": {},
        "image": {
            "pic1": "https://dkstatics-public.digikala.com/digikala-products/48ed6ca66f990787de0027635e87e5a85047108a_1712700959.jpg?x-oss-process=image/resize,m_lfit,h_800,w_800/quality,q_90"
        },
        "attributes": [
            {
                "key": "جنس",
                "value": [
                    "پنبه یکرو"
                ]
            },
            {
                "key": "طرح",
                "value": [
                    "چاپ"
                ]
            },
            {
                "key": "قد",
                "value": [
                    "روی کمر"
                ]
            },
            {
                "key": "تنخور لباس",
                "value": [
                    "معمولی"
                ]
            },
            {
                "key": "مدل یقه",
                "value": [
                    "گرد"
                ]
            },
            {
                "key": "نوع آستین",
                "value": [
                    "کوتاه"
                ]
            },
            {
                "key": "مورد استفاده",
                "value": [
                    "اسپرت"
                ]
            }
        ]
    }
]