[
    {
        "id": 5252052,
        "title_fa": "تی شرت آستین کوتاه زنانه به رسم مدل unlock کد 5406",
        "price": {},
        "image": {
            "pic1": "https://dkstatics-public.digikala.com/digikala-products/c2496b017e29988930ff757e03213a601e28b4b4_1621764793.jpg?x-oss-process=image/resize,m_lfit,h_800,w_800/quality,q_90"
        },
        "attributes": [
            {
                "key": "جنس",
                "value": [
                    "پلی استر",
                    "نخ"
                ]
            },
            {
                "key": "طرح",
                "value": [
                    "چاپ"
                ]
            },
            {
                "key": "قد",
                "value": [
                    "روی باسن"
                ]
            },
            {
                "key": "تنخور لباس",
                "value": [
                    "معمولی"
                ]
            },
            {
                "key": "مدل یقه",
                "value": [
                    "گرد"
                ]
            },
            {
                "key": "نوع آستین",
                "value": [
                    "کوتاه"
                ]
            },
            {
                "key": "مورد استفاده",
                "value": [
                    "روزمره"
                ]
            }
        ]
    }
]