[
    {
        "id": 8449471,
        "title_fa": "تی شرت آستین بلند زنانه مدل گنجشک کد J142",
        "price": {},
        "image": {
            "pic1": "https://dkstatics-public.digikala.com/digikala-products/77c3ac9e5f08636cfe33a14388de37f337317067_1651905391.jpg?x-oss-process=image/resize,m_lfit,h_800,w_800/quality,q_90"
        },
        "attributes": [
            {
                "key": "جنس",
                "value": [
                    "الیاف نخی",
                    "پلی استر"
                ]
            },
            {
                "key": "طرح",
                "value": [
                    "چاپ"
                ]
            },
            {
                "key": "قد",
                "value": [
                    "روی باسن"
                ]
            },
            {
                "key": "تنخور لباس",
                "value": [
                    "معمولی"
                ]
            },
            {
                "key": "مدل یقه",
                "value": [
                    "گرد"
                ]
            },
            {
                "key": "نوع آستین",
                "value": [
                    "بلند"
                ]
            },
            {
                "key": "مورد استفاده",
                "value": [
                    "اسپرت",
                    "روزمره",
                    "مهمانی"
                ]
            }
        ]
    }
]