[
    {
        "id": 9195081,
        "title_fa": "تی شرت آستین کوتاه زنانه اسمارا مدل A67",
        "price": {},
        "image": {
            "pic1": "https://dkstatics-public.digikala.com/digikala-products/76d276ea21a2bf7410010981c10e31597a36a659_1660467147.jpg?x-oss-process=image/resize,m_lfit,h_800,w_800/quality,q_90"
        },
        "attributes": [
            {
                "key": "جنس",
                "value": [
                    "کتان"
                ]
            },
            {
                "key": "طرح",
                "value": [
                    "ساده"
                ]
            },
            {
                "key": "قد",
                "value": [
                    "روی باسن"
                ]
            },
            {
                "key": "تنخور لباس",
                "value": [
                    "معمولی"
                ]
            },
            {
                "key": "مدل یقه",
                "value": [
                    "گرد"
                ]
            },
            {
                "key": "نوع آستین",
                "value": [
                    "کوتاه"
                ]
            },
            {
                "key": "مورد استفاده",
                "value": [
                    "اسپرت",
                    "روزمره",
                    "اداری و رسمی",
                    "مهمانی"
                ]
            }
        ]
    }
]