[
    {
        "id": 11195703,
        "title_fa": "ناموجودتی شرت آستین کوتاه ورزشی زنانه مدل FC4B26B8",
        "price": {},
        "image": {
            "pic1": "https://dkstatics-public.digikala.com/digikala-products/3920230dfe3d96cab44ebe68f4c0c6b84dfb08b0_1682776673.jpg?x-oss-process=image/resize,m_lfit,h_800,w_800/quality,q_90"
        },
        "attributes": [
            {
                "key": "جنس",
                "value": [
                    "پلی استر"
                ]
            },
            {
                "key": "طرح",
                "value": [
                    "چاپ"
                ]
            },
            {
                "key": "قد",
                "value": [
                    "روی باسن"
                ]
            },
            {
                "key": "مدل یقه",
                "value": [
                    "گرد"
                ]
            },
            {
                "key": "نوع آستین",
                "value": [
                    "کوتاه"
                ]
            },
            {
                "key": "تنخور لباس",
                "value": [
                    "معمولی"
                ]
            },
            {
                "key": "نگهداری",
                "value": [
                    "با دمای حداکثر ۳۰ درجه سانتی گراد شستشو شود.\r\nبا دمای کم اتوکشی شود.\r\nخشکشویی نشود.\r\nاز خشک کن استفاده نشود.\r\nاز سفید کننده استفاده نشود."
                ]
            }
        ]
    }
]