[
    {
        "id": 16438110,
        "title_fa": "کراپ تی شرت ورزشی زنانه استولز مدل S81",
        "price": {},
        "image": {
            "pic1": "https://dkstatics-public.digikala.com/digikala-products/3e8e0d220db6f065b28c6530080ec800930c72f2_1723782815.jpg?x-oss-process=image/resize,m_lfit,h_800,w_800/quality,q_90"
        },
        "attributes": [
            {
                "key": "نوع تی شرت ورزشی زنانه",
                "value": [
                    "تی شرت ورزشی"
                ]
            },
            {
                "key": "جنس",
                "value": [
                    "پلی استر"
                ]
            },
            {
                "key": "طرح",
                "value": [
                    "ساده"
                ]
            },
            {
                "key": "قد",
                "value": [
                    "روی کمر"
                ]
            },
            {
                "key": "مدل یقه",
                "value": [
                    "گرد"
                ]
            },
            {
                "key": "نوع آستین",
                "value": [
                    "کوتاه"
                ]
            },
            {
                "key": "تنخور لباس",
                "value": [
                    "آزاد"
                ]
            }
        ]
    }
]