[
    {
        "id": 2306499,
        "title_fa": "ناموجودتیشرت ورزشی زنانه کد Z-SE32",
        "price": {},
        "image": {
            "pic1": "https://dkstatics-public.digikala.com/digikala-products/117704591.jpg?x-oss-process=image/resize,m_lfit,h_800,w_800/quality,q_90"
        },
        "attributes": [
            {
                "key": "جنس",
                "value": [
                    "ویسکوز"
                ]
            },
            {
                "key": "مدل یقه",
                "value": [
                    "گرد"
                ]
            },
            {
                "key": "نوع آستین",
                "value": [
                    "کوتاه"
                ]
            },
            {
                "key": "جزئیات",
                "value": [
                    "فرم دهی به بدن \r\nعبور هوا و کمک به تعریق بدن \r\nخشک شدن سریع بعد از شستشو"
                ]
            },
            {
                "key": "نگهداری",
                "value": [
                    "اتوکشی در دمای متوسط \r\nشستشو در دمای ۴۰ درجه سانتیگراد"
                ]
            },
            {
                "key": "کشور مبدا برند",
                "value": [
                    "آلمان"
                ]
            },
            {
                "key": "کشور تولید کننده",
                "value": [
                    "بنگلادش"
                ]
            }
        ]
    }
]