[
    {
        "id": 3442955,
        "title_fa": "ناموجودتیشرت ورزشی زنانه مدل x44",
        "price": {},
        "image": {
            "pic1": "https://dkstatics-public.digikala.com/digikala-products/52173219d491e6bca4fefeb2eaeae8df453f2f60_1600841651.jpg?x-oss-process=image/resize,m_lfit,h_800,w_800/quality,q_90"
        },
        "attributes": [
            {
                "key": "جنس",
                "value": [
                    "پلی استر",
                    "پلی آمید"
                ]
            },
            {
                "key": "طرح",
                "value": [
                    "ساده",
                    "طرح‌دار"
                ]
            },
            {
                "key": "قد",
                "value": [
                    "روی باسن"
                ]
            },
            {
                "key": "مدل یقه",
                "value": [
                    "گرد"
                ]
            },
            {
                "key": "نوع آستین",
                "value": [
                    "کوتاه"
                ]
            },
            {
                "key": "تنخور لباس",
                "value": [
                    "معمولی"
                ]
            },
            {
                "key": "کد کالای محصول",
                "value": [
                    "X۴۴"
                ]
            },
            {
                "key": "کشور مبدا برند",
                "value": [
                    "آلمان"
                ]
            },
            {
                "key": "کشور تولید کننده",
                "value": [
                    "آلمان"
                ]
            }
        ]
    }
]