[
    {
        "id": 3563026,
        "title_fa": "ناموجودتی شرت ورزشی زنانه مدل 4041",
        "price": {},
        "image": {
            "pic1": "https://dkstatics-public.digikala.com/digikala-products/4d9e2ee21b9faae92247e3f4fe0e2b82e8edbf4c_1602796290.jpg?x-oss-process=image/resize,m_lfit,h_800,w_800/quality,q_90"
        },
        "attributes": [
            {
                "key": "جنس",
                "value": [
                    "پلی آمید"
                ]
            },
            {
                "key": "طرح",
                "value": [
                    "ساده"
                ]
            },
            {
                "key": "قد",
                "value": [
                    "روی کمر"
                ]
            },
            {
                "key": "مدل یقه",
                "value": [
                    "گرد"
                ]
            },
            {
                "key": "نوع آستین",
                "value": [
                    "کوتاه"
                ]
            },
            {
                "key": "تنخور لباس",
                "value": [
                    "جذب"
                ]
            }
        ]
    }
]