[
    {
        "id": 5021551,
        "title_fa": "ناموجودتی شرت ورزشی زنانه مدل 1814",
        "price": {},
        "image": {
            "pic1": "https://dkstatics-public.digikala.com/digikala-products/7579f39a96d90ac64a25b4df3fdf8b39476568ec_1619535518.jpg?x-oss-process=image/resize,m_lfit,h_800,w_800/quality,q_90"
        },
        "attributes": [
            {
                "key": "جنس",
                "value": [
                    "الاستین",
                    "ویسکوز"
                ]
            },
            {
                "key": "طرح",
                "value": [
                    "طرح‌دار"
                ]
            },
            {
                "key": "قد",
                "value": [
                    "روی باسن"
                ]
            },
            {
                "key": "مدل یقه",
                "value": [
                    "گرد"
                ]
            },
            {
                "key": "نوع آستین",
                "value": [
                    "کوتاه"
                ]
            },
            {
                "key": "تنخور لباس",
                "value": [
                    "معمولی"
                ]
            },
            {
                "key": "کد کالای محصول",
                "value": [
                    "۱۸۱۴"
                ]
            },
            {
                "key": "کشور مبدا برند",
                "value": [
                    "آلمان"
                ]
            },
            {
                "key": "کشور تولید کننده",
                "value": [
                    "آلمان"
                ]
            }
        ]
    }
]