[
    {
        "id": 5023271,
        "title_fa": "ناموجودتی شرت ورزشی زنانه مدل 1818",
        "price": {},
        "image": {
            "pic1": "https://dkstatics-public.digikala.com/digikala-products/301a869cdef490237e34fd1e60b0eb9b0858c29a_1619526502.jpg?x-oss-process=image/resize,m_lfit,h_800,w_800/quality,q_90"
        },
        "attributes": [
            {
                "key": "جنس",
                "value": [
                    "الاستین",
                    "ویسکوز"
                ]
            },
            {
                "key": "طرح",
                "value": [
                    "ساده"
                ]
            },
            {
                "key": "قد",
                "value": [
                    "روی باسن"
                ]
            },
            {
                "key": "مدل یقه",
                "value": [
                    "گرد"
                ]
            },
            {
                "key": "نوع آستین",
                "value": [
                    "کوتاه"
                ]
            },
            {
                "key": "تنخور لباس",
                "value": [
                    "معمولی"
                ]
            },
            {
                "key": "کد کالای محصول",
                "value": [
                    "۱۸۱۸"
                ]
            },
            {
                "key": "کشور مبدا برند",
                "value": [
                    "آلمان"
                ]
            },
            {
                "key": "کشور تولید کننده",
                "value": [
                    "آلمان"
                ]
            }
        ]
    }
]