[
    {
        "id": 6951243,
        "title_fa": "تی شرت آستین کوتاه ورزشی زنانه مدل 3607-023",
        "price": {},
        "image": {
            "pic1": "https://dkstatics-public.digikala.com/digikala-products/65c44bdb37ad4330fe68ebcbe7103399532fb819_1636196636.jpg?x-oss-process=image/resize,m_lfit,h_800,w_800/quality,q_90"
        },
        "attributes": [
            {
                "key": "جنس",
                "value": [
                    "فلامنت"
                ]
            },
            {
                "key": "طرح",
                "value": [
                    "ساده"
                ]
            },
            {
                "key": "قد",
                "value": [
                    "روی باسن"
                ]
            },
            {
                "key": "مدل یقه",
                "value": [
                    "گرد"
                ]
            },
            {
                "key": "نوع آستین",
                "value": [
                    "کوتاه"
                ]
            },
            {
                "key": "تنخور لباس",
                "value": [
                    "جذب"
                ]
            }
        ]
    }
]