[
    {
        "id": 7474526,
        "title_fa": "ناموجودتی شرت آستین بلند ورزشی زنانه نیچرهایک مدل NH19FS023",
        "price": {},
        "image": {
            "pic1": "https://dkstatics-public.digikala.com/digikala-products/931c40c8133082de7eacdb88c0bcc99d8a5c3e10_1642317825.jpg?x-oss-process=image/resize,m_lfit,h_800,w_800/quality,q_90"
        },
        "attributes": [
            {
                "key": "جنس",
                "value": [
                    "اکریلیک",
                    "اسپاندکس",
                    "نایلون",
                    "ویسکوز"
                ]
            },
            {
                "key": "طرح",
                "value": [
                    "ساده"
                ]
            },
            {
                "key": "قد",
                "value": [
                    "روی باسن"
                ]
            },
            {
                "key": "مدل یقه",
                "value": [
                    "گرد"
                ]
            },
            {
                "key": "نوع آستین",
                "value": [
                    "بلند"
                ]
            },
            {
                "key": "تنخور لباس",
                "value": [
                    "جذب"
                ]
            },
            {
                "key": "جزئیات",
                "value": [
                    "آنتی باکتریال , امکان خشک شدن سریع , فرم دهی به بدن , قابلیت گردش هوا\r\nدرزهای صاف هنگام پوشیدن باعث افزایش راحتی می شوند. سرآستین ها، گردن و پایین محصول نیز صاف است که با یک درز الاستیک پوشیده می شود. تناسب کاملی را برای هر بدن فراهم می کند."
                ]
            },
            {
                "key": "کد کالای محصول",
                "value": [
                    "NH۱۹FS۰۲۳"
                ]
            },
            {
                "key": "کشور تولید کننده",
                "value": [
                    "چین"
                ]
            }
        ]
    }
]