[
    {
        "id": 9773360,
        "title_fa": "ناموجودتی شرت آستین کوتاه ورزشی زنانه مدل Euro 2020",
        "price": {},
        "image": {
            "pic1": "https://dkstatics-public.digikala.com/digikala-products/526aaceb5d37194e8a6a02f2dd01066d9da9126e_1667244928.jpg?x-oss-process=image/resize,m_lfit,h_800,w_800/quality,q_90"
        },
        "attributes": [
            {
                "key": "جنس",
                "value": [
                    "الاستین",
                    "پنبه"
                ]
            },
            {
                "key": "طرح",
                "value": [
                    "چاپ"
                ]
            },
            {
                "key": "قد",
                "value": [
                    "روی باسن"
                ]
            },
            {
                "key": "مدل یقه",
                "value": [
                    "هفت"
                ]
            },
            {
                "key": "نوع آستین",
                "value": [
                    "کوتاه"
                ]
            },
            {
                "key": "تنخور لباس",
                "value": [
                    "معمولی"
                ]
            },
            {
                "key": "کشور تولید کننده",
                "value": [
                    "بنگلادش"
                ]
            }
        ]
    }
]