[
    {
        "id": 10652972,
        "title_fa": "ناموجودتی شرت آستین کوتاه زنانه مدل 8934",
        "price": {},
        "image": {
            "pic1": "https://dkstatics-public.digikala.com/digikala-products/bc9396ca3814a5f4b18a416920e00e7cbcf2d116_1676446431.jpg?x-oss-process=image/resize,m_lfit,h_800,w_800/quality,q_90"
        },
        "attributes": [
            {
                "key": "جنس",
                "value": [
                    "الیاف نخی"
                ]
            },
            {
                "key": "طرح",
                "value": [
                    "ساده"
                ]
            },
            {
                "key": "قد",
                "value": [
                    "روی باسن"
                ]
            },
            {
                "key": "مدل یقه",
                "value": [
                    "گرد"
                ]
            },
            {
                "key": "نوع آستین",
                "value": [
                    "بدون آستین"
                ]
            },
            {
                "key": "تنخور لباس",
                "value": [
                    "معمولی"
                ]
            },
            {
                "key": "جزئیات",
                "value": [
                    "این محصول فری سایز و دارای دور کمر (مانکن): ۷۵ سانتی متر، دور سینه (مانکن): ۹۰ سانتی متر، سرشانه (مانکن): ۱۷ سانتی متر، عرض شانه (مانکن) ۴۷ سانتی متر، ارتفاع/ طول (مانکن): ۷۵ سانتی متر، نوع آستین: بدون آستین، قد آستین: ۰ سانتی متر، ارتفاع/طول (محصول): ۶۴ سانتی متر، عرض/پهنا (محصول): ۴۲ سانتی متر، نوع یقه: یقه گرد مهره دار، رنگ: قرمز، وزن: ۱۶۶ گرم و از جنس الیاف نخی با حالت کشسانی (مناسب سایز های مختلف) می باشد."
                ]
            },
            {
                "key": "کد کالای محصول",
                "value": [
                    "۸۹۳۴"
                ]
            }
        ]
    }
]