[
    {
        "id": 11605742,
        "title_fa": "ناموجودتی شرت زنانه مدل نخ پنبه پولکدوزی",
        "price": {},
        "image": {
            "pic1": "https://dkstatics-public.digikala.com/digikala-products/f10f4125b0d2f11c4816c7a7ead16ef4d228bf91_1686239554.jpg?x-oss-process=image/resize,m_lfit,h_800,w_800/quality,q_90"
        },
        "attributes": [
            {
                "key": "جنس",
                "value": [
                    "پنبه",
                    "نخ"
                ]
            },
            {
                "key": "طرح",
                "value": [
                    "تکه‌دوزی"
                ]
            },
            {
                "key": "قد",
                "value": [
                    "روی باسن"
                ]
            },
            {
                "key": "مدل یقه",
                "value": [
                    "گرد"
                ]
            },
            {
                "key": "نوع آستین",
                "value": [
                    "کوتاه"
                ]
            },
            {
                "key": "تنخور لباس",
                "value": [
                    "معمولی"
                ]
            },
            {
                "key": "جزئیات",
                "value": [
                    "تیشرت زنانه آستین کوتاه پولکدوزی کيفيت عالی در رنگ و طرح های مختلف\r\nدور سینه ۱۰۲ سانت"
                ]
            }
        ]
    }
]