[
    {
        "id": 16394965,
        "title_fa": "تاپ زنانه مدل ایلا کد 09",
        "price": {},
        "image": {
            "pic1": "https://dkstatics-public.digikala.com/digikala-products/d90d1141229ceb2ff9781569df70a2b93c57cde4_1723557447.jpg?x-oss-process=image/resize,m_lfit,h_800,w_800/quality,q_90"
        },
        "attributes": [
            {
                "key": "نوع تاپ و تی‌شرت راحتی زنانه",
                "value": [
                    "تاپ راحتی"
                ]
            },
            {
                "key": "جنس",
                "value": [
                    "اسپان"
                ]
            },
            {
                "key": "طرح",
                "value": [
                    "ساده"
                ]
            },
            {
                "key": "قد",
                "value": [
                    "روی باسن"
                ]
            },
            {
                "key": "مدل یقه",
                "value": [
                    "گرد"
                ]
            },
            {
                "key": "نوع آستین",
                "value": [
                    "بدون آستین"
                ]
            },
            {
                "key": "تنخور لباس",
                "value": [
                    "جذب"
                ]
            }
        ]
    }
]