[
    {
        "id": 4923768,
        "title_fa": "ناموجودتاپ زنانه کد 7",
        "price": {},
        "image": {
            "pic1": "https://dkstatics-public.digikala.com/digikala-products/09dc4a6764cdca233dbfeabb8b34483294610c19_1618604952.jpg?x-oss-process=image/resize,m_lfit,h_800,w_800/quality,q_90"
        },
        "attributes": [
            {
                "key": "جنس",
                "value": [
                    "ویسکوز"
                ]
            },
            {
                "key": "طرح",
                "value": [
                    "طرح‌دار"
                ]
            },
            {
                "key": "قد",
                "value": [
                    "روی کمر"
                ]
            },
            {
                "key": "مدل یقه",
                "value": [
                    "گرد"
                ]
            },
            {
                "key": "نوع آستین",
                "value": [
                    "بدون آستین"
                ]
            },
            {
                "key": "تنخور لباس",
                "value": [
                    "معمولی"
                ]
            },
            {
                "key": "نگهداری",
                "value": [
                    "عدم شستشو با آب بسیار داغ"
                ]
            }
        ]
    }
]