[
    {
        "id": 6284100,
        "title_fa": "ناموجودتی شرت آستین کوتاه زنانه میس نگار کد 222",
        "price": {},
        "image": {
            "pic1": "https://dkstatics-public.digikala.com/digikala-products/97798e90bab4a7c99a5dcb1d9dedbd6cc6626f35_1630436986.jpg?x-oss-process=image/resize,m_lfit,h_800,w_800/quality,q_90"
        },
        "attributes": [
            {
                "key": "جنس",
                "value": [
                    "الیاف نخی",
                    "لاکرا",
                    "ویسکوز"
                ]
            },
            {
                "key": "طرح",
                "value": [
                    "چاپ"
                ]
            },
            {
                "key": "قد",
                "value": [
                    "روی باسن"
                ]
            },
            {
                "key": "مدل یقه",
                "value": [
                    "گرد"
                ]
            },
            {
                "key": "نوع آستین",
                "value": [
                    "کوتاه"
                ]
            },
            {
                "key": "تنخور لباس",
                "value": [
                    "معمولی"
                ]
            },
            {
                "key": "کد کالای محصول",
                "value": [
                    "۲۲۲"
                ]
            },
            {
                "key": "کشور تولید کننده",
                "value": [
                    "ایران"
                ]
            }
        ]
    }
]