[
    {
        "id": 12069124,
        "title_fa": "نیم تنه زنانه مدل گیپور حورا فانتزی رنگ سرمه ای",
        "price": {},
        "image": {
            "pic1": "https://dkstatics-public.digikala.com/digikala-products/e979d8b1b7fa46a4d408c40b9f7a3071caf3e9b6_1689530679.jpg?x-oss-process=image/resize,m_lfit,h_800,w_800/quality,q_90"
        },
        "attributes": [
            {
                "key": "جنس",
                "value": [
                    "گیپور"
                ]
            },
            {
                "key": "طرح",
                "value": [
                    "طرح‌دار"
                ]
            },
            {
                "key": "قد",
                "value": [
                    "نیم تنه"
                ]
            },
            {
                "key": "مدل یقه",
                "value": [
                    "باز"
                ]
            },
            {
                "key": "نوع آستین",
                "value": [
                    "بدون آستین"
                ]
            },
            {
                "key": "تنخور لباس",
                "value": [
                    "جذب"
                ]
            },
            {
                "key": "مورد استفاده",
                "value": [
                    "اسپرت",
                    "روزمره",
                    "اداری و رسمی",
                    "مهمانی"
                ]
            }
        ]
    }
]