[
    {
        "id": 13940796,
        "title_fa": "تاپ زنانه اسمارا مدل tak1",
        "price": {},
        "image": {
            "pic1": "https://dkstatics-public.digikala.com/digikala-products/e5b814b95fab40a55f9734c6d3dbb254b4ee6635_1703932631.jpg?x-oss-process=image/resize,m_lfit,h_800,w_800/quality,q_90"
        },
        "attributes": [
            {
                "key": "جنس",
                "value": [
                    "الاستین",
                    "نخ"
                ]
            },
            {
                "key": "طرح",
                "value": [
                    "طرح‌دار"
                ]
            },
            {
                "key": "قد",
                "value": [
                    "روی باسن"
                ]
            },
            {
                "key": "مدل یقه",
                "value": [
                    "گرد"
                ]
            },
            {
                "key": "نوع آستین",
                "value": [
                    "حلقه‌ای"
                ]
            },
            {
                "key": "تنخور لباس",
                "value": [
                    "معمولی"
                ]
            },
            {
                "key": "مورد استفاده",
                "value": [
                    "اسپرت",
                    "روزمره"
                ]
            }
        ]
    }
]