[
    {
        "id": 9379436,
        "title_fa": "تاپ زنانه مدل SBK-1646",
        "price": {},
        "image": {
            "pic1": "https://dkstatics-public.digikala.com/digikala-products/ebedff4c629d262e3486b24a8af89ee9e8051039_1662373749.jpg?x-oss-process=image/resize,m_lfit,h_800,w_800/quality,q_90"
        },
        "attributes": [
            {
                "key": "جنس",
                "value": [
                    "نخ"
                ]
            },
            {
                "key": "طرح",
                "value": [
                    "طرح‌دار"
                ]
            },
            {
                "key": "قد",
                "value": [
                    "روی باسن"
                ]
            },
            {
                "key": "مدل یقه",
                "value": [
                    "گرد"
                ]
            },
            {
                "key": "نوع آستین",
                "value": [
                    "حلقه‌ای"
                ]
            },
            {
                "key": "تنخور لباس",
                "value": [
                    "جذب"
                ]
            },
            {
                "key": "ویژگی‌های تخصصی",
                "value": [
                    "امکان خشک شدن سریع",
                    "قابلیت گردش هوا",
                    "انعطاف پذیر"
                ]
            },
            {
                "key": "مورد استفاده",
                "value": [
                    "اسپرت",
                    "روزمره"
                ]
            },
            {
                "key": "جزئیات",
                "value": [
                    "تن خور Slim Fit جذب\r\nطرح طرح‌دار\r\nطرح پارچه طرح دار\r\nجنس\tنخی\r\nاستایل اسپرت, روزمره\r\nمورد استفاده استفاده روزانه, میهمانی دوستانه\r\nفصل استفاده بهار, تابستان\r\nجنسیت زنانه\r\nنوع محصول\t تاپ\r\nمدل یقه گرد\r\nنوع آستین\tآستین حلقه‌ ای"
                ]
            },
            {
                "key": "نگهداری",
                "value": [
                    "می توانید این لباس را به هر ۲ صورت دستی و به وسیله ماشین رختشویی بشویید\r\nبهتر است لباس های رنگی خود را بصورت جداگانه بشویید.\r\nاز دمای بالاتر از ۳۰ درجه سانتیگراد برای شست و شوی این لباس خانگی استفاده نکنید.\r\nتوجه داشته باشید که سفید کننده ها و پودر های آنزیم دار می توانند به الیاف لباس آسیب وارد نمایند.\r\nتوصیه می شود از خشک کن برای خشک کردن لباس استفاده نکنید.\r\nاین دسته از لباس ها نیاز به اتو کردن ندارند در صورت نیاز از درجه حرارت پایین استفاده نمایید."
                ]
            }
        ]
    }
]